releaseme/version.py
releaseme/runner.py
releaseme/sh.py
releaseme/__init__.py
releaseme/errors.py
releaseme/__main__.py
releaseme-0.2.8.dist-info/metadata.json
releaseme-0.2.8.dist-info/METADATA
releaseme-0.2.8.dist-info/WHEEL
releaseme-0.2.8.dist-info/RECORD
releaseme-0.2.8.dist-info/top_level.txt
releaseme-0.2.8.dist-info/DESCRIPTION.rst
