Metadata-Version: 2.0
Name: releaseme
Version: 0.2.8
Summary: Library and command line app to manage project releases or versions
Home-page: https://github.com/magmax/python-releaseme
Author: Miguel Ángel García
Author-email: miguelangel.garcia@gmail.com
License: MIT
Keywords: version,versions,versioning,release,releasing
Platform: UNKNOWN
Classifier: Development Status :: 4 - Beta
Classifier: Environment :: Console
Classifier: Intended Audience :: Developers
Classifier: License :: OSI Approved :: MIT License
Classifier: Operating System :: OS Independent
Requires-Dist: pluginloader (>=0.1.2)
